text_excuse_generator/__init__.py
text_excuse_generator/excuse_generator.py
text_excuse_generator-1.1.5.1.dist-info/LICENSE
text_excuse_generator-1.1.5.1.dist-info/METADATA
text_excuse_generator-1.1.5.1.dist-info/WHEEL
text_excuse_generator-1.1.5.1.dist-info/top_level.txt
text_excuse_generator-1.1.5.1.dist-info/RECORD
