Metadata-Version: 2.1
Name: text-excuse-generator
Version: 1.1.5.1
Summary: Uses Open AI's GPT-3.5 model to create an excuse from given parameters & text it
Home-page: https://github.com/Huckdirks/text-excuse-generator
Author: Huck Dirksmeier
Author-email: Huckdirks@gmail.com
Keywords: text excuse generator,openai,twilio,text message,GPT-3.5
Classifier: Programming Language :: Python
Classifier: License :: OSI Approved :: MIT License
Classifier: Operating System :: OS Independent
Requires-Python: >=3.8
License-File: LICENSE
Requires-Dist: python-dotenv
Requires-Dist: twilio
Requires-Dist: openai
Requires-Dist: phonenumbers
